isegeval/__init__.py
isegeval/click/__init__.py
isegeval/click/factories.py
isegeval/click/factory.py
isegeval/click/strategies.py
isegeval/click/strategy.py
isegeval/core.py
isegeval/utils.py
isegeval-0.1.0.dist-info/LICENSE
isegeval-0.1.0.dist-info/WHEEL
isegeval-0.1.0.dist-info/METADATA
isegeval-0.1.0.dist-info/RECORD
