Metadata-Version: 2.1
Name: isegeval
Version: 0.1.0
Summary: A Python Library to Evaluate Interactive Segmentation Models
Home-page: https://github.com/tech-sketch/isegeval
License: MIT
Author: yasufumi
Author-email: yasufumi.taniguchi@gmail.com
Requires-Python: >=3.8.1,<4.0
Classifier: License :: OSI Approved :: MIT License
Classifier: Programming Language :: Python
Classifier: Programming Language :: Python :: 3
Classifier: Programming Language :: Python :: 3.10
Classifier: Programming Language :: Python :: 3.8
Classifier: Programming Language :: Python :: 3.9
Requires-Dist: numpy (>=1.23.5,<2.0.0)
Requires-Dist: scipy (>=1.9.3,<2.0.0)
Requires-Dist: tqdm (>=4.64.1,<5.0.0)
Project-URL: Repository, https://github.com/tech-sketch/isegeval
